sms_ir/__init__.py
sms_ir/mixins.py
sms_ir/services.py
smsir_python-1.0.7.dist-info/LICENCE
smsir_python-1.0.7.dist-info/METADATA
smsir_python-1.0.7.dist-info/WHEEL
smsir_python-1.0.7.dist-info/top_level.txt
smsir_python-1.0.7.dist-info/RECORD
