Metadata-Version: 2.1
Name: smsir-python
Version: 1.0.7
Summary: Python Package of SMS.ir Panel 
Home-page: https://github.com/IPeCompany/SmsPanelV2.Python
Author: Mojtaba Akbari
Author-email: mojtaba.akbari.221b@gmail.com
License: MIT
Requires-Python: >=3.7
License-File: LICENCE
